odoo/addons/base_user_show_email/README.rst
odoo/addons/base_user_show_email/__init__.py
odoo/addons/base_user_show_email/__manifest__.py
odoo/addons/base_user_show_email/i18n/base_user_show_email.pot
odoo/addons/base_user_show_email/i18n/it.po
odoo/addons/base_user_show_email/readme/CONTRIBUTORS.rst
odoo/addons/base_user_show_email/readme/DESCRIPTION.rst
odoo/addons/base_user_show_email/static/description/icon.png
odoo/addons/base_user_show_email/static/description/index.html
odoo/addons/base_user_show_email/views/login_layout.xml
odoo/addons/base_user_show_email/views/res_users_view.xml
odoo14_addon_base_user_show_email-14.0.1.0.1.dev5.dist-info/METADATA
odoo14_addon_base_user_show_email-14.0.1.0.1.dev5.dist-info/WHEEL
odoo14_addon_base_user_show_email-14.0.1.0.1.dev5.dist-info/top_level.txt
odoo14_addon_base_user_show_email-14.0.1.0.1.dev5.dist-info/RECORD
